onnxcli/__init__.py
onnxcli/check.py
onnxcli/common.py
onnxcli/convert.py
onnxcli/dispatcher.py
onnxcli/draw.py
onnxcli/extract.py
onnxcli/infer_shape.py
onnxcli/inspect.py
onnxcli/optimize.py
onnxcli/setup.py
onnxcli-0.2.1.dist-info/LICENSE
onnxcli-0.2.1.dist-info/METADATA
onnxcli-0.2.1.dist-info/WHEEL
onnxcli-0.2.1.dist-info/entry_points.txt
onnxcli-0.2.1.dist-info/top_level.txt
onnxcli-0.2.1.dist-info/RECORD
