Metadata-Version: 2.1
Name: onnxcli
Version: 0.2.1
Summary: Lightweight Command Line Toolbox for ONNX
Home-page: https://zhenhuaw.me/onnxcli
Author: 王振华(Zhenhua WANG)
Author-email: hi@zhenhuaw.me
License: Apache License 2.0
Project-URL: Bug Reports, https://github.com/zhenhuaw-me/onnxcli/issues
Project-URL: Source, https://github.com/zhenhuaw-me/onnxcli
Keywords: onnx,deep-learning
Classifier: Development Status :: 3 - Alpha
Classifier: Programming Language :: Python :: 3
Classifier: Programming Language :: Python :: 3.6
Classifier: Programming Language :: Python :: 3.7
Classifier: Programming Language :: Python :: 3.8
Classifier: Environment :: Console
Classifier: Intended Audience :: Developers
Classifier: License :: OSI Approved :: Apache Software License
Classifier: Natural Language :: English
Classifier: Operating System :: OS Independent
Classifier: Topic :: Scientific/Engineering :: Artificial Intelligence
Requires-Python: <4,>=3.6.*
License-File: LICENSE
Requires-Dist: onnx
